{
	"Version": 3,
	"Parameters": [
		{
			"Id": "ParamAngleX",
			"GroupId": "",
			"Name": "角度 X"
		},
		{
			"Id": "ParamAngleY",
			"GroupId": "",
			"Name": "角度 Y"
		},
		{
			"Id": "ParamAngleZ",
			"GroupId": "",
			"Name": "角度 Z"
		},
		{
			"Id": "ParamEyeLOpen",
			"GroupId": "",
			"Name": "左眼 开闭"
		},
		{
			"Id": "ParamEyeLSmile",
			"GroupId": "",
			"Name": "左眼 微笑"
		},
		{
			"Id": "ParamEyeROpen",
			"GroupId": "",
			"Name": "右眼 开闭"
		},
		{
			"Id": "ParamEyeRSmile",
			"GroupId": "",
			"Name": "右眼 微笑"
		},
		{
			"Id": "ParamEyeBallX",
			"GroupId": "",
			"Name": "眼珠 X"
		},
		{
			"Id": "ParamEyeBallY",
			"GroupId": "",
			"Name": "眼珠 Y"
		},
		{
			"Id": "ParamBrowLY",
			"GroupId": "",
			"Name": "左眉 上下"
		},
		{
			"Id": "ParamBrowLX",
			"GroupId": "",
			"Name": "左眉 左右"
		},
		{
			"Id": "ParamBrowRY",
			"GroupId": "",
			"Name": "右眉 上下"
		},
		{
			"Id": "ParamBrowLAngle",
			"GroupId": "",
			"Name": "左眉 角度"
		},
		{
			"Id": "ParamBrowRX",
			"GroupId": "",
			"Name": "右眉 左右"
		},
		{
			"Id": "ParamBrowRAngle",
			"GroupId": "",
			"Name": "右眉 角度"
		},
		{
			"Id": "ParamBrowLForm",
			"GroupId": "",
			"Name": "左眉 変形"
		},
		{
			"Id": "ParamBrowRForm",
			"GroupId": "",
			"Name": "右眉 変形"
		},
		{
			"Id": "ParamMouthForm",
			"GroupId": "",
			"Name": "嘴 变形"
		},
		{
			"Id": "ParamMouthOpenY",
			"GroupId": "",
			"Name": "嘴 开闭"
		},
		{
			"Id": "ParamCheek",
			"GroupId": "",
			"Name": "脸颊泛红"
		},
		{
			"Id": "Param8",
			"GroupId": "",
			"Name": "大头"
		},
		{
			"Id": "ParamBodyAngleX",
			"GroupId": "",
			"Name": "身体旋转 X"
		},
		{
			"Id": "ParamBodyAngleY",
			"GroupId": "",
			"Name": "身体旋转 Y"
		},
		{
			"Id": "ParamBodyAngleZ",
			"GroupId": "",
			"Name": "身体旋转 Z"
		},
		{
			"Id": "ParamHairFront",
			"GroupId": "",
			"Name": "摇动 前发"
		},
		{
			"Id": "ParamHairSide",
			"GroupId": "",
			"Name": "摇动 侧发"
		},
		{
			"Id": "ParamHairBack",
			"GroupId": "",
			"Name": "摇动 后发"
		},
		{
			"Id": "Param",
			"GroupId": "",
			"Name": "左手"
		},
		{
			"Id": "Param2",
			"GroupId": "",
			"Name": "右手"
		},
		{
			"Id": "Param3",
			"GroupId": "",
			"Name": "左耳环"
		},
		{
			"Id": "Param4",
			"GroupId": "",
			"Name": "右耳环"
		},
		{
			"Id": "Param5",
			"GroupId": "",
			"Name": "扭腰"
		},
		{
			"Id": "Param6",
			"GroupId": "",
			"Name": "呼吸"
		},
		{
			"Id": "Param7",
			"GroupId": "",
			"Name": "项链"
		},
		{
			"Id": "Param9",
			"GroupId": "",
			"Name": "左鬓角"
		},
		{
			"Id": "Param10",
			"GroupId": "",
			"Name": "右鬓角"
		}
	],
	"ParameterGroups": [],
	"Parts": [],
	"CombinedParameters": [
		[
			"ParamMouthForm",
			"ParamMouthOpenY"
		]
	]
}